battery/__init__.py
battery/__init__.pyi
battery/__main__.py
battery/battery.json
battery/battery.toml
battery-1.0.3.dist-info/METADATA
battery-1.0.3.dist-info/WHEEL
battery-1.0.3.dist-info/licenses/LICENSE.md
battery-1.0.3.dist-info/RECORD
