Metadata-Version: 2.3
Name: battery
Version: 1.0.3
Summary: Cross-platform battery status
Project-URL: Homepage, https://github.com/yunruse/battery
Project-URL: Bug Tracker, https://github.com/yunruse/battery/issues
Author-email: Mia yun Ruse <mia@yunru.se>
License-Expression: LicenseRef-Public-Domain
License-File: LICENSE.md
Keywords: battery,cross-platform
Classifier: License :: Public Domain
Classifier: Operating System :: MacOS
Classifier: Operating System :: Microsoft :: Windows
Classifier: Operating System :: POSIX :: Linux
Classifier: Programming Language :: Python :: 3.7
Classifier: Topic :: System
Classifier: Topic :: System :: Hardware
Classifier: Typing :: Stubs Only
Requires-Python: >=3.7
